{
    "Ar36": {
        "error": 0.0026282607293975926,
        "error_type": "SEM",
        "filter_outliers_dict": {
            "filter_outliers": true,
            "iterations": 2,
            "std_devs": 2
        },
        "fit": "Parabolic",
        "value": 1.1854598746258576
    },
    "Ar37": {
        "error": 0.014816012272733747,
        "error_type": "SEM",
        "filter_outliers_dict": {
            "filter_outliers": true,
            "iterations": 2,
            "std_devs": 2
        },
        "fit": "linear",
        "value": 0.09588814193883678
    },
    "Ar38": {
        "error": 0.0043713445948162484,
        "error_type": "SEM",
        "filter_outliers_dict": {
            "filter_outliers": true,
            "iterations": 2,
            "std_devs": 2
        },
        "fit": "linear",
        "value": 0.31480555114867564
    },
    "Ar39": {
        "error": 0.01354088894927442,
        "error_type": "SEM",
        "filter_outliers_dict": {
            "filter_outliers": true,
            "iterations": 2,
            "std_devs": 2
        },
        "fit": "Parabolic",
        "value": -0.026433370150507503
    },
    "Ar40": {
        "error": 0.05126112297704652,
        "error_type": "SEM",
        "filter_outliers_dict": {
            "filter_outliers": true,
            "iterations": 2,
            "std_devs": 2
        },
        "fit": "Parabolic",
        "value": 358.5764176422614
    }
}